dict2object/__init__.py
dict2object/dict2object.py
dict2object_gaponukz-0.0.5.dist-info/LICENSE
dict2object_gaponukz-0.0.5.dist-info/METADATA
dict2object_gaponukz-0.0.5.dist-info/WHEEL
dict2object_gaponukz-0.0.5.dist-info/top_level.txt
dict2object_gaponukz-0.0.5.dist-info/RECORD
