Metadata-Version: 2.1
Name: dict2object-gaponukz
Version: 0.0.5
Summary: Convert dict to (js)object
Home-page: https://github.com/gaponukz/dict2object
Author: Eugene Gaponyuk
Author-email: gaponukz54@gmail.com
License: UNKNOWN
Platform: UNKNOWN
Classifier: Programming Language :: Python :: 3.10
Classifier: License :: OSI Approved :: MIT License
Classifier: Operating System :: OS Independent
Requires-Python: >=3.8
License-File: LICENSE
